clever_cloud/__init__.py
clever_cloud/auth.py
clever_cloud/client.py
clever_cloud/exceptions.py
clever_cloud/models.py
clever_cloud/oauth_dance.py
clevercloud_sdk-0.1.0.dist-info/METADATA
clevercloud_sdk-0.1.0.dist-info/WHEEL
clevercloud_sdk-0.1.0.dist-info/licenses/LICENSE
clevercloud_sdk-0.1.0.dist-info/RECORD
