Metadata-Version: 2.4
Name: clevercloud-sdk
Version: 0.1.0
Summary: Python SDK for the Clever Cloud API
Project-URL: Homepage, https://github.com/CleverCloud/clevercloud-sdk-python
Project-URL: Documentation, https://github.com/CleverCloud/clevercloud-sdk-python#readme
Project-URL: Repository, https://github.com/CleverCloud/clevercloud-sdk-python
Project-URL: Issues, https://github.com/CleverCloud/clevercloud-sdk-python/issues
Author-email: Clever Cloud <support@clever-cloud.com>
License-Expression: Apache-2.0
License-File: LICENSE
Keywords: api,clever-cloud,cloud,paas,sdk
Classifier: Development Status :: 4 - Beta
Classifier: Intended Audience :: Developers
Classifier: License :: OSI Approved :: Apache Software License
Classifier: Operating System :: OS Independent
Classifier: Programming Language :: Python :: 3
Classifier: Programming Language :: Python :: 3.10
Classifier: Programming Language :: Python :: 3.11
Classifier: Programming Language :: Python :: 3.12
Classifier: Programming Language :: Python :: 3.13
Classifier: Topic :: Internet :: WWW/HTTP
Classifier: Topic :: Software Development :: Libraries :: Python Modules
Classifier: Typing :: Typed
Requires-Python: >=3.10
Requires-Dist: httpx>=0.25.0
